pypandoc/__init__.py
pypandoc/handler.py
pypandoc/pandoc_download.py
pypandoc/py3compat.py
pypandoc-1.9.dist-info/LICENSE
pypandoc-1.9.dist-info/METADATA
pypandoc-1.9.dist-info/WHEEL
pypandoc-1.9.dist-info/top_level.txt
pypandoc-1.9.dist-info/RECORD
